{
  "app_name": "Golang Microservice Template",
  "service_name": "{{ cookiecutter.app_name.lower().replace(' ', '-') }}",
  "system_code": "{{ cookiecutter.service_name }}",
  "repo_name": "{{ cookiecutter.system_code }}",
  "docker_image": "coco/{{ cookiecutter.system_code }}",
  "project_short_description": "UPP Golang Microservice Template short description - please amend",
  "github_username": "your_name",
  "deploy_to_delivery_cluster": "y/n",
  "deploy_to_publishing_cluster": "y/n",
  "add_sample_http_endpoint": ["yes", "no"]
}
